{"name":"Youtube-embed-joomla","tagline":"Embed youtube videos in joomla 2.5+ by pasting the youtube url in articles. ","body":"### Youtube Embed for Joomla\r\nYoutube Embed is a plugin for Joomla 2.5 and 3.0. This is a easy way to create embedded videos fro youtube. Simply paste the url, and we will embed it for you! \r\n\r\n### How to install?\r\n1. Download the plugin (left)\r\n2. Install the plugin in Joomal 2.5 or higher\r\n3. Go to \"Extensions -> Plugin manager -> Content - Youtube Embed\" and enable it. \r\n4. We hav ealso created some settings for you\r\n\r\n### Have fun\r\nIf you need any help to get fun, please create a ticket under \"Issues\" here at the github repo! :) ","google":"","note":"Don't delete this file! It's used internally to help with page regeneration."}